locotoml/__init__.py
locotoml/core.py
locotoml/py.typed
locotoml-0.2.0.dist-info/METADATA
locotoml-0.2.0.dist-info/WHEEL
locotoml-0.2.0.dist-info/RECORD
