Metadata-Version: 2.1
Name: locotoml
Version: 0.2.0
Summary: LocoTOML is a lightweight Python library for multi-language support, using hierarchical TOML-based translations with fallback and detailed logging for missing keys.
Home-page: https://github.com/drago-suzuki58/LocoTOML
License: MIT
Keywords: toml,localization,translation,localisation,multi-language
Author: drago-suzuki58
Author-email: dorasuzu58@gmail.com
Requires-Python: >=3.11,<4.0
Classifier: License :: OSI Approved :: MIT License
Classifier: Programming Language :: Python :: 3
Classifier: Programming Language :: Python :: 3.11
Classifier: Programming Language :: Python :: 3.12
Requires-Dist: lococore (>=0.2.0,<0.3.0)
Requires-Dist: toml (>=0.10.2,<0.11.0)
Project-URL: Issues, https://github.com/drago-suzuki58/LocoTOML/issues
Project-URL: Repository, https://github.com/drago-suzuki58/LocoTOML
